tableModel/__init__.py
tableModel/tableStyles.py
simple_qtable_model-0.1.4.dist-info/METADATA
simple_qtable_model-0.1.4.dist-info/WHEEL
simple_qtable_model-0.1.4.dist-info/top_level.txt
simple_qtable_model-0.1.4.dist-info/RECORD
